<annotation>
	<folder>JPEGImages</folder>
	<filename>0070.jpg</filename>
	<path>E:\Workspace\PycharmProjects\yolov5-tf2-main\VOCdevkit\VOC2007\JPEGImages\0070.jpg</path>
	<source>
		<database>Unknown</database>
	</source>
	<size>
		<width>960</width>
		<height>540</height>
		<depth>3</depth>
	</size>
	<segmented>0</segmented>
	<object>
		<name>mask</name>
		<pose>Unspecified</pose>
		<truncated>0</truncated>
		<difficult>0</difficult>
		<bndbox>
			<xmin>513</xmin>
			<ymin>77</ymin>
			<xmax>790</xmax>
			<ymax>421</ymax>
		</bndbox>
	</object>
	<object>
		<name>mask</name>
		<pose>Unspecified</pose>
		<truncated>0</truncated>
		<difficult>0</difficult>
		<bndbox>
			<xmin>25</xmin>
			<ymin>190</ymin>
			<xmax>290</xmax>
			<ymax>461</ymax>
		</bndbox>
	</object>
</annotation>
