<annotation>
	<folder>JPEGImages</folder>
	<filename>289.jpg</filename>
	<path>E:\Workspace\PycharmProjects\yolov5-tf2-main\VOCdevkit\VOC2007\JPEGImages\289.jpg</path>
	<source>
		<database>Unknown</database>
	</source>
	<size>
		<width>1024</width>
		<height>1155</height>
		<depth>3</depth>
	</size>
	<segmented>0</segmented>
	<object>
		<name>person</name>
		<pose>Unspecified</pose>
		<truncated>0</truncated>
		<difficult>0</difficult>
		<bndbox>
			<xmin>280</xmin>
			<ymin>59</ymin>
			<xmax>413</xmax>
			<ymax>195</ymax>
		</bndbox>
	</object>
	<object>
		<name>person</name>
		<pose>Unspecified</pose>
		<truncated>0</truncated>
		<difficult>0</difficult>
		<bndbox>
			<xmin>493</xmin>
			<ymin>39</ymin>
			<xmax>644</xmax>
			<ymax>195</ymax>
		</bndbox>
	</object>
</annotation>
