<annotation>
	<folder>jpgimage</folder>
	<filename>582.jpg</filename>
	<path>E:\Workspace\PycharmProjects\yolov5-tf2-main\VOCdevkit\VOC2007\jpgimage\582.jpg</path>
	<source>
		<database>Unknown</database>
	</source>
	<size>
		<width>333</width>
		<height>500</height>
		<depth>3</depth>
	</size>
	<segmented>0</segmented>
	<object>
		<name>person</name>
		<pose>Unspecified</pose>
		<truncated>0</truncated>
		<difficult>0</difficult>
		<bndbox>
			<xmin>151</xmin>
			<ymin>136</ymin>
			<xmax>193</xmax>
			<ymax>178</ymax>
		</bndbox>
	</object>
	<object>
		<name>person</name>
		<pose>Unspecified</pose>
		<truncated>0</truncated>
		<difficult>0</difficult>
		<bndbox>
			<xmin>94</xmin>
			<ymin>194</ymin>
			<xmax>129</xmax>
			<ymax>234</ymax>
		</bndbox>
	</object>
</annotation>
